{"intents": [
    {
    "tag": "noanswer",
    "patterns": [""],
    "responses": ["maaf saya tidak tau", "tolong beri saya info lebih detail", "saya tidak paham"],
    "context": [""]
   },
    {"tag": "DBD",
     "patterns": ["sakit","demam tinggi pada beberapa hari", "sakit pada persendian", "munculnya bintik-bintik merah", "turunnya trombosit secara drastis", "pendarahan"],
     "responses": ["Hello, thanks for asking", "Good to see you again", "Hi there, how can I help?"],
     "context": [""]
    },
    {"tag": "maag",
     "patterns": ["sakit","nyeri","ulu","hati", "mual", "muntah", "muntah setelah makan"],
     "responses": ["See you!", "Have a nice day", "Bye! Come back again soon."],
     "context": [""]
    },
    {"tag": "Muntaber",
     "patterns": ["Thanks", "Thank you", "That's helpful", "Awesome, thanks", "Thanks for helping me"],
     "responses": ["Happy to help!", "Any time!", "My pleasure"],
     "context": [""]
    },
    {"tag": "Cacar air",
     "patterns": ["How you could help me?", "What you can do?", "What help you provide?", "How you can be helpful?", "What support is offered"],
     "responses": ["I can guide you through Adverse drug reaction list, Blood pressure tracking, Hospitals and Pharmacies", "Offering support for Adverse drug reaction, Blood pressure, Hospitals and Pharmacies"],
     "context": [""]
    },
    {"tag": "Tifus",
     "patterns": ["How to check Adverse drug reaction?", "Open adverse drugs module", "Give me a list of drugs causing adverse behavior", "List all drugs suitable for patient with adverse reaction", "Which drugs dont have adverse reaction?" ],
     "responses": ["Navigating to Adverse drug reaction module"],
     "context": [""]
    },
    {
     "tag": "influenza",
     "patterns": ["Open blood pressure module", "Task related to blood pressure", "Blood pressure data entry", "I want to log blood pressure results", "Blood pressure data management" ],
     "responses": ["Navigating to Blood Pressure module"],
     "context": [""]
    },
    {"tag": "PES / Pesteurellosi",
     "patterns": ["I want to search for blood pressure result history", "Blood pressure for patient", "Load patient blood pressure result", "Show blood pressure results for patient", "Find blood pressure results by ID" ],
     "responses": ["Please provide Patient ID", "Patient ID?"],
     "context": ["search_blood_pressure_by_patient_id"]
    },
    {"tag": "Kolera",
     "patterns": [],
     "responses": ["Loading Blood pressure result for Patient"],
     "context": [""]
    }
]
}